en_tasta_bot_ingredients_guillaumeoj/__init__.py
en_tasta_bot_ingredients_guillaumeoj/meta.json
en_tasta_bot_ingredients_guillaumeoj/en_tasta_bot_ingredients_guillaumeoj-0.2.1/README.md
en_tasta_bot_ingredients_guillaumeoj/en_tasta_bot_ingredients_guillaumeoj-0.2.1/config.cfg
en_tasta_bot_ingredients_guillaumeoj/en_tasta_bot_ingredients_guillaumeoj-0.2.1/meta.json
en_tasta_bot_ingredients_guillaumeoj/en_tasta_bot_ingredients_guillaumeoj-0.2.1/tokenizer
en_tasta_bot_ingredients_guillaumeoj/en_tasta_bot_ingredients_guillaumeoj-0.2.1/ner/cfg
en_tasta_bot_ingredients_guillaumeoj/en_tasta_bot_ingredients_guillaumeoj-0.2.1/ner/model
en_tasta_bot_ingredients_guillaumeoj/en_tasta_bot_ingredients_guillaumeoj-0.2.1/ner/moves
en_tasta_bot_ingredients_guillaumeoj/en_tasta_bot_ingredients_guillaumeoj-0.2.1/tok2vec/cfg
en_tasta_bot_ingredients_guillaumeoj/en_tasta_bot_ingredients_guillaumeoj-0.2.1/tok2vec/model
en_tasta_bot_ingredients_guillaumeoj/en_tasta_bot_ingredients_guillaumeoj-0.2.1/vocab/key2row
en_tasta_bot_ingredients_guillaumeoj/en_tasta_bot_ingredients_guillaumeoj-0.2.1/vocab/lookups.bin
en_tasta_bot_ingredients_guillaumeoj/en_tasta_bot_ingredients_guillaumeoj-0.2.1/vocab/strings.json
en_tasta_bot_ingredients_guillaumeoj/en_tasta_bot_ingredients_guillaumeoj-0.2.1/vocab/vectors
en_tasta_bot_ingredients_guillaumeoj/en_tasta_bot_ingredients_guillaumeoj-0.2.1/vocab/vectors.cfg
en_tasta_bot_ingredients_guillaumeoj-0.2.1.dist-info/METADATA
en_tasta_bot_ingredients_guillaumeoj-0.2.1.dist-info/WHEEL
en_tasta_bot_ingredients_guillaumeoj-0.2.1.dist-info/entry_points.txt
en_tasta_bot_ingredients_guillaumeoj-0.2.1.dist-info/top_level.txt
en_tasta_bot_ingredients_guillaumeoj-0.2.1.dist-info/RECORD
