Metadata-Version: 2.1
Name: en_tasta_bot_ingredients_guillaumeoj
Version: 0.2.1
Home-page: 
Author: 
Author-email: 
Requires-Dist: spacy <3.8.0,>=3.7.5
